DateTF/__init__.py
DateTF/core.py
datetf-0.1.0.dist-info/licenses/LICENSE
datetf-0.1.0.dist-info/METADATA
datetf-0.1.0.dist-info/WHEEL
datetf-0.1.0.dist-info/top_level.txt
datetf-0.1.0.dist-info/RECORD
