Metadata-Version: 2.4
Name: DateTF
Version: 0.1.0
Summary: This module provides two lightweight, immutable date wrapper classes — MonthEndDate and WeekendDate
Author: TF
License: MIT
Requires-Python: >=3.8
License-File: LICENSE
Dynamic: license-file
